migbq/BQMig.py
migbq/BigQueryForwarder.py
migbq/BigQueryJobChecker.py
migbq/DummyForwarder.py
migbq/Forwarder.py
migbq/MigrationConfig.py
migbq/MigrationMetadataManager.py
migbq/MigrationRoot.py
migbq/MigrationSet.py
migbq/MsSqlDatasource.py
migbq/MySqlDatasource.py
migbq/__init__.py
migbq/migutils.py
migbq/peewee_mssql_custom.py
migbq-0.0.85.dist-info/DESCRIPTION.rst
migbq-0.0.85.dist-info/METADATA
migbq-0.0.85.dist-info/RECORD
migbq-0.0.85.dist-info/WHEEL
migbq-0.0.85.dist-info/entry_points.txt
migbq-0.0.85.dist-info/metadata.json
migbq-0.0.85.dist-info/top_level.txt
