Metadata-Version: 2.0
Name: migbq
Version: 0.0.85
Summary: read microsoft sql server table data and upload to bigquery
Home-page: https://github.com/jo8937/migbq
Author: jo8937
Author-email: jo8937@gmail.com
License: MIT
Platform: UNKNOWN
Requires-Python: >=2.7
Requires-Dist: ujson (>=1.35)
Requires-Dist: peewee (==2.8.5)
Requires-Dist: pymssql (>=2.1.1)
Requires-Dist: peewee-mssql (>=0.1.0)
Requires-Dist: concurrent-log-handler (>=0.9.8)
Requires-Dist: pyyaml (>=3.12)
Requires-Dist: google-cloud-bigquery (==0.27.0)
Requires-Dist: Jinja2 (>=2.10)
Requires-Dist: httplib2
